[
  {
    "id": "3c8ff398-3703-4a13-9e2b-8b7f70064c1e",
    "data": [
      {
        "text": "How to get secured against Authentication at a central location ?",
        "userDefined": false
      }
    ],
    "isTemplate": false,
    "count": 0,
    "updated": 0
  },
  {
    "id": "e2eebbf3-0cd5-46d2-9d0e-b258284c2603",
    "data": [
      {
        "text": "How to defend Authentication at a central location ?",
        "userDefined": false
      }
    ],
    "isTemplate": false,
    "count": 0,
    "updated": 0
  },
  {
    "id": "fe9bb437-b284-4517-b341-64541373f88e",
    "data": [
      {
        "text": "How to stop Authentication at a central location ?",
        "userDefined": false
      }
    ],
    "isTemplate": false,
    "count": 0,
    "updated": 0
  },
  {
    "id": "120ed102-164d-4a98-940e-bab8d97fe55d",
    "data": [
      {
        "text": "How to mitigate Authentication at a central location ?",
        "userDefined": false
      }
    ],
    "isTemplate": false,
    "count": 0,
    "updated": 0
  },
  {
    "id": "055e180b-b98d-4787-b442-7c731dd3ea54",
    "data": [
      {
        "text": "How to resolve Authentication at a central location ?",
        "userDefined": false
      }
    ],
    "isTemplate": false,
    "count": 0,
    "updated": 0
  },
  {
    "id": "1b73e78c-003c-4050-aaf1-fab173d3e735",
    "data": [
      {
        "text": "How to solve Authentication at a central location ?",
        "userDefined": false
      }
    ],
    "isTemplate": false,
    "count": 0,
    "updated": 0
  }
]