[
  {
    "id": "89e6f7f8-5b12-4982-aad5-581e205814c0",
    "data": [
      {
        "text": "How to get secured against Client side state management ?",
        "userDefined": false
      }
    ],
    "isTemplate": false,
    "count": 0,
    "updated": 0
  },
  {
    "id": "fce7d836-9755-4ff4-844b-5ab850d9ccc5",
    "data": [
      {
        "text": "How to defend Client side state management ?",
        "userDefined": false
      }
    ],
    "isTemplate": false,
    "count": 0,
    "updated": 0
  },
  {
    "id": "16554a3d-b8e5-4917-916e-0c7e13e5a6f6",
    "data": [
      {
        "text": "How to stop Client side state management ?",
        "userDefined": false
      }
    ],
    "isTemplate": false,
    "count": 0,
    "updated": 0
  },
  {
    "id": "a2393cb8-a602-4f08-81e9-5a1473a57a94",
    "data": [
      {
        "text": "How to mitigate Client side state management ?",
        "userDefined": false
      }
    ],
    "isTemplate": false,
    "count": 0,
    "updated": 0
  },
  {
    "id": "c4bb81d1-b620-4390-9ca5-93b41f9149c1",
    "data": [
      {
        "text": "How to resolve Client side state management ?",
        "userDefined": false
      }
    ],
    "isTemplate": false,
    "count": 0,
    "updated": 0
  },
  {
    "id": "0a765050-94cf-4a91-8bde-fe0b5ba5fb20",
    "data": [
      {
        "text": "How to solve Client side state management ?",
        "userDefined": false
      }
    ],
    "isTemplate": false,
    "count": 0,
    "updated": 0
  }
]